pyautoinstall/__init__.py
pyautoinstall-0.0.1.dist-info/LICENSE
pyautoinstall-0.0.1.dist-info/WHEEL
pyautoinstall-0.0.1.dist-info/METADATA
pyautoinstall-0.0.1.dist-info/RECORD
