Metadata-Version: 2.1
Name: pyautoinstall
Version: 0.0.1
Summary: Magically install modules just by importing them!!
Home-page: https://github.com/ajratnam/pyautoinstall
License: MIT
Keywords: auto,install,import,pip
Author: Ajay Ratnam
Author-email: ajayratnam.satheesh@gmail.com
Maintainer: Ajay Ratnam
Maintainer-email: ajayratnam.satheesh@gmail.com
Requires-Python: >=3.9,<4.0
Classifier: Development Status :: 1 - Planning
Classifier: Intended Audience :: Developers
Classifier: License :: OSI Approved
Classifier: License :: OSI Approved :: MIT License
Classifier: Natural Language :: English
Classifier: Programming Language :: Python
Classifier: Programming Language :: Python :: 3
Classifier: Programming Language :: Python :: 3.9
Classifier: Programming Language :: Python :: Implementation
Classifier: Programming Language :: Python :: Implementation :: CPython
Classifier: Topic :: Software Development
Classifier: Topic :: Software Development :: Libraries
Classifier: Topic :: Software Development :: Libraries :: Python Modules
Classifier: Topic :: Software Development :: Version Control
Classifier: Topic :: Software Development :: Version Control :: Git
Classifier: Topic :: Utilities
Project-URL: Documentation, https://github.com/ajratnam/pyautoinstall
Project-URL: Repository, https://github.com/ajratnam/pyautoinstall
